ts2pi/__init__.py
ts2pi/tda.py
ts2pi-0.1.4.dist-info/LICENSE.txt
ts2pi-0.1.4.dist-info/METADATA
ts2pi-0.1.4.dist-info/WHEEL
ts2pi-0.1.4.dist-info/top_level.txt
ts2pi-0.1.4.dist-info/RECORD
