Metadata-Version: 2.1
Name: ts2pi
Version: 0.1.4
Summary: Python module to transform a time series into a persistence image representation
Home-page: https://github.com/clementpiat/time-series-persistence-image
Author: Clement Piat
License: UNKNOWN
Platform: UNKNOWN
Requires-Dist: numpy (>=1.19)
Requires-Dist: gudhi (==3.4.1)
Requires-Dist: sklearn (==0.0)
